{"id": "678036669c3ba90f51dc61fa", "source": "juritj", "text": "Tribunal de Proximité\n[Adresse 2]\n[Adresse 8]\n[Localité 6]\ntel : [XXXXXXXX01]\n[Courriel 9]\n\n\n\n\nN° RG 24/00213 - N° Portalis DBZ3-W-B7I-75XGW\n\nMinute : 24/00439 \n\n\nDÉSISTEMENT\n\nDu : \n\n\n\n\nM. [W] [M]\n\n\nC/\n\nS.A.R.L. PB DEVELOPPEMENT\n\n\n\n\nDÉCISION DE DÉSISTEMENT\n\n(Articles 394 et 395 Code de Procédure Civile)\n\n\n\nDANS L'AFFAIRE OPPOSANT :\n\n\nM. [W] [M]\n[Adresse 4]\n[Localité 5]\nreprésenté par Me Audrey LESAGE, avocat au barreau de BOULOGNE-SUR-MER\n\n\n\n\nà :\n\n\nS.A.R.L. PB DEVELOPPEMENT\n[Adresse 3]\n[Localité 7]\n\nreprésentée par Me Hervé LECLERCQ, avocat au barreau de BOULOGNE-SUR-MER\n\n\n\n\n\n▸ Constate que le demandeur a déclaré expressément se désister d'instance et d'action ;\n\n▸ Décide que les frais de l'instance éteinte seront supportés par le demandeur.\n\nAinsi jugé en audience publique le 05 Novembre 2024 par Charles DRAPEAU, juge des contentieux de la protection, assisté de Yannick LANCE, greffier.\n\n\nLe greffier, Le président", "jurisdiction": "tj", "chamber": "CALAIS contentieux<10000€", "number": "24/00213", "numbers": ["24/00213"], "location": "tj62160", "decision_date": "2024-11-05", "decision_datetime": "2024-11-05T00:00:00.000Z", "update_date": "2025-01-09", "update_datetime": "2025-01-09T20:48:01.541Z", "solution": "Constate ou prononce le désistement d'instance et/ou d'action", "type": "other", "nac": "56C", "portalis": null, "files": [], "zones": {"introduction": [{"start": 0, "end": 613}], "dispositif": [{"start": 613, "end": 929}]}, "contested": null, "forward": null, "timeline": null, "partial": false, "visa": [], "rapprochements": [], "legacy": {}, "titlesAndSummaries": [], "particularInterest": false}