{"id": "67bf6cc3f1062435dd1699d9", "source": "juritj", "text": "TRIBUNAL JUDICIAIRE DE MARSEILLE\n\nPôle de Proximité\n\n\n\n\n\n\nJUGEMENT DU : 02 Septembre 2024\nPrésident : Monsieur BOTTERO, Vice-Président\nGreffier : Mme SCANNAPIECO,\nDébats en audience publique le : 03 Juin 2024\n\n\n\n GROSSE :\n Le 02/09/24\n à Me GUILLET\n Le ...................................................\n à Me ...............................................\nLe ...................................................\n à Me ...............................................\n EXPEDITION :\n Le ..........................................................\n à Me ......................................................\n Le ..........................................................\n à Me ......................................................\nLe ...........................................................\n à Me ......................................................\n\n\nN° RG 24/00889 - N° Portalis DBW3-W-B7I-4QHL\n\nPARTIES :\n\nDEMANDERESSE\n\nS.A. CEPAC, dont le siège social est sis [Adresse 4]\n\nreprésentée par Me Paul GUILLET, avocat au barreau de MARSEILLE\n\n\nDEFENDEUR\n\nMonsieur [N] [F]\nné le [Date naissance 1] 1990 à [Localité 3], demeurant [Adresse 2]\n\nnon comparant\n\n\n\n\n\n\n\n\n\n\n\n\n\n\n\n \nEXPOSE DU LITIGE\n\n\nPar acte du 10 janvier 2024, Société CAISSE D'EPARGNE CEPAC a assigné [F] [N] devant le juge des contentieux de la protection de MARSEILLE, pour les motifs suivants tels qu’ils résultent de son acte introductif d’instance.\n\nSelon offre de contrat signée le 21 mai 2019, la Société CAISSE D'EPARGNE CEPAC consentait à [F] [N] un contrat de prêt personnel d’un montant de 14000 € au taux de 2,60 % l’an. \n\n[F] [N] s’est montré défaillant dans le respect de ses obligations si bien que la déchéance du terme a été prononcée le 15 décembre 2023.\n\nLors de l’audience du 3 juin 2024, Société CAISSE D'EPARGNE CEPAC s’est référée à son assignation et a demandé au juge des contentieux de la protection de MARSEILLE, sur le fondement des articles R 312-35, L 312-39 et D 312-16 du code de la consommation, de :\n\n-Constater la résiliation du contrat de prêt-Condamner [F] [N] à lui payer la somme de 9475,52 € avec intérêt au taux contractuel de 2,60 % à compter du 15 décembre 2023 avec capitalisation des intérêts;-Condamner [F] [N] à lui payer la somme de 500,00€ sur le fondement de l'article 700 du code de procédure civile.-Condamner [F] [N] au paiement des entiers dépens.Ordonner l’exécution provisoire\n\nCité par acte de commissaire de justice remis à étude, [F] [N] n’a pas comparu.\n\nLa présente décision sera réputée contradictoire, conformément à l'article 473 du code de procédure civile.\n\n\nMOTIFS\n\n\nConformément à l’article 472 du code de procédure civile, si le défendeur ne comparaît pas, le juge est fondé à statuer sur le fond et à faire droit à la demande dans la mesure où il l’estime régulière, recevable et bien fondée.\n\n\nSur la créance de Société CAISSE D'EPARGNE CEPAC:\n\nL’article L311-30 du code de la consommation dispose que, « en cas de défaillance de l’emprunteur, le prêteur pourra exiger le remboursement immédiat du capital existant dû, majoré des intérêts échus mais non payés.\nJusqu’à la date du règlement effectif, les sommes restant dues produisent les intérêts de retard à un taux égal à celui du prêt ».\n\nEn l’espèce, Société CAISSE D'EPARGNE CEPAC soutient que [F] [N] lui doit la somme de :\nla somme de 9475,52 € avec intérêt au taux contractuel de 2,60% à compter du 15 décembre 2023 avec capitalisation des intérêts\nSociété CAISSE D'EPARGNE CEPAC fournit au dossier le contrat souscrit par [F] [N] ainsi qu’un historique comptable.\n\nLe contrat contient une clause résolutoire en cas de non paiement.\n\nCes éléments corroborent son allégation.\n\n[F] [N] , non comparant, ne fournit aucun élément au dossier de nature à contester la dette.\n\nLa demande de Société CAISSE D'EPARGNE CEPAC qui ne se heurte à aucune contestation sérieuse ne peut qu’être accueillie.\n\nPar conséquent, il y a lieu de faire droit à la demande de Société CAISSE D'EPARGNE CEPAC, de constater la résiliation du contrat et de condamner [F] [N] à lui payer les sommes de :\n9475,52 € avec intérêt au taux contractuel de 2,60% à compter du 15 décembre 2023;\nEn revanche, il n’y a pas lieu à ordonner la capitalisation des intérêts\n\nSur les dépens, l’article 700 du code de procédure civile et l’exécution provisoire\n\n[F] [N] , qui succombe, sera tenu aux dépens.\n\nAucune considération tirée de l'équité ou de la situation économique des parties ne justifie qu'il soit accordé une indemnité au titre des dispositions de l'article 700 du code de procédure civile.\n\nLes couts d’exécution forcée, purement hypothétiques à ce stade, ne seront pas mis à la charge du défendeur.\n\nIl convient de rappeler que la présente décision est exécutoire à titre provisoire, conformément aux articles 514 et 514-1 du code de procédure civile.\n\n\n\nPAR CES MOTIFS\n\n\nLe juge des contentieux de la protection, statuant publiquement par mise à disposition au greffe, par jugement réputé contradictoire et en premier ressort,\n\nConstate la résiliation du contrat de prêt signé le 21 mai 2019 ;\n\nCondamne [F] [N] à payer à Société CAISSE D'EPARGNE CEPAC la somme de 9475,52 € avec intérêt au taux contractuel de 2,60% à compter du 15 décembre 2023 ;\n\nRejette les demandes supplémentaires ou contraires ;\n\nCondamne [F] [N] aux dépens ;\n\nDit n’y avoir lieu à l’application de l’article 700 du code de procédure civile ;\n\nRappelle que le présent jugement est de droit exécutoire à titre provisoire ;\n\nAINSI JUGE ET PRONONCE LES JOURS MOIS ET AN QUE DESSUS\n\nLe greffier Le juge des contentieux de la protection", "jurisdiction": "tj", "chamber": "0P10 Aud. civile prox 1", "number": "24/00889", "numbers": ["24/00889"], "location": "tj13055", "decision_date": "2024-06-03", "decision_datetime": "2024-06-03T00:00:00.000Z", "update_date": "2025-02-26", "update_datetime": "2025-02-26T19:34:08.954Z", "solution": "Délibéré pour mise à disposition de la décision", "type": "other", "nac": "53B", "portalis": null, "files": [], "zones": {"introduction": [{"start": 0, "end": 1158}], "expose": [{"start": 1158, "end": 2586}], "motivations": [{"start": 2586, "end": 4820}], "dispositif": [{"start": 4820, "end": 5572}]}, "contested": null, "forward": null, "timeline": null, "partial": false, "visa": [], "rapprochements": [], "legacy": {}, "titlesAndSummaries": [], "particularInterest": false}