{"id": "67d4acd6a68a7746ee75343b", "source": "juritj", "text": "MINUTE N° : \nJUGEMENT DU : 14 Mars 2025\nDOSSIER : N° RG 24/00878 - N° Portalis DB3J-W-B7I-GJ55\n\n\nTRIBUNAL JUDICIAIRE DE POITIERS\n\nPREMIÈRE CHAMBRE CIVILE\n\nSelon la procédure orale, sans représentation obligatoire\n\nCOMPOSITION DU TRIBUNAL\n\nPRESIDENT :\nMadame RIGUET Johanna,\n\nGREFFIER :\nMadame GRANSAGNE Marine,\n\nPARTIES :\n\nDEMANDERESSE\n\nS.C.I. HERFLO, \ndont le siège social est sis [Adresse 2]\n\nreprésentée par M. [U] [M] et Mme [W] [E] épouse [M]\n\n\nDEFENDEUR\n\nCopie exécutoire délivrée\nLe \nà SCI HERFLO\nà\n\nCopie certifiée conforme \ndélivrée le \nà SCI HERFLO\nà etablissement [F]\n\n\n \nETABLISSEMENT [F], \ndont le siège social est sis [Adresse 1]\n\nnon comparant ni représenté\n\n\n\nDÉBATS TENUS À L'AUDIENCE DU : 10 JANVIER 2025\n\n\nJUGEMENT RENDU PAR MISE À DISPOSITION AU GREFFE LE QUATORZE MARS DEUX MIL VINGT CINQ\nDOSSIER N° : N° RG 24/00878 - N° Portalis DB3J-W-B7I-GJ55 Page \nEXPOSE DU LITIGE\n\nLa SCI HERFLO a mandaté ETABLISSEMENT [F] afin de changer une porte de service en acier galvanisé pour un montant total de 1733 €.\n\nUn acompte d’un montant de 866.50 € a été effectué en date du 23 mai 2023 (facture N°14 du 23 mai 2023)\n\nEn l’absence d’exécution des travaux, par lettre recommandée avec avis de réception en date du 30 novembre 2023, la SCI HERFLO a sollicité l’annulation de la commande et le remboursement de l’acompte auprès du représentant de l’ETABLISSEMENT [F].\nEn date du 13 mars 2024, un constat de carence a été établi.\n\nPar requête en date 23 mars 2024, la SCI HERFLO a saisi le tribunal judiciaire de Poitiers, en demandant sur le fondement de l’article 1217 du code civil la résolution du contrat et le remboursement de l’acompte déjà versé.\n\nLors de l'audience du 10 janvier 2025, la SCI HERFLO comparant en personne, confirme les termes de sa demande initiale. \n\nEn défense, régulièrement assigné selon les modalités de l'article 659 du code de procédure civile, l’ETABLISSEMENT [F] n'a pas comparu et ne s'est pas fait représenter. \n\nA l'issue de l'audience, la date du délibéré a été fixée au 14 mars 2025.\n\nMOTIFS DE LA DECISION\n\nSur la non comparution du défendeur\n\nEn application des dispositions de l'article 472 du code de procédure civile, lorsque le défendeur ne comparaît pas, il est néanmoins statué sur le fond, le juge ne faisant droit à la demande que s'il l'estime recevable, régulière et bien fondée.\n\nLe défendeur non comparant ayant été régulièrement assigné et ayant disposé d'un temps suffisant pour organiser sa défense, il y a lieu de statuer par jugement par réputé contradictoire et en premier ressort.\n\nSur la résolution du contrat\n\nL’article 1217 du code civil dispose que La partie envers laquelle l'engagement n'a pas été exécuté, ou l'a été imparfaitement, peut provoquer la résolution du contrat.\nL’article 1227 du même code dispose que « La résolution peut, en toute hypothèse, être demandée en justice. »\n\nL’article 1228 du code civil énonce que « Le juge peut, selon les circonstances, constater ou prononcer la résolution ou ordonner l'exécution du contrat, en accordant éventuellement un délai au débiteur, ou allouer seulement des dommages et intérêts. »\n\nEn l’espèce, il ressort de la facture en date du 23 mai 2023 que l’ETABLISSEMENT [F] s’est engagé à changer une porte de service moyennant une somme de 1733 € au total. La SCI HERFLO a versé un acompte de 866.50 € à la commande. Il ressort du courrier en date 30 novembre 2023, que le délai maximum fixé pour réaliser les travaux étaient de 6 à 8 semaines soit courant juillet 2023.\n\nLa SCI HERFLO a notifié par lettre recommandée à Monsieur [F] [B] représentant de l’établissement [F], l’inexécution de ses obligations et la demande de remboursement de l’acompte versé.\n\nLe défendeur, non comparant, n’apporte par définition aucun élément de nature à contester ni la non-exécution de ses obligations ni la nature ou le montant de la créance.\n\nEn conséquence, le tribunal prononce la résolution du contrat matérialisé par la facture N°14 en date du 25 mai 2013 et devis N°47, à compter de la présente décision et condamne l’ETABLISSEMENT [F] à rembourser à la SCI HERFLO la somme de 866.50 € correspondant à l’acompte versé par cette dernière conformément à l’article 1229 du code civil.\n\nSur la demande de dommages et intérêts\n\nLa SCI HERFLO demande la somme de 600 € au titre des frais engagés à l'occasion d'une instance non compris dans les dépens. En l’espèce, ses frais de transport pour venir à l’audience et ses frais de repas.\n\nLa SCI HERFLO étant domiciliée dans le sud de la France, il serait inéquitable de lui laisser à sa charge des frais qu’elle a dû engager pour faire valoir ses droits. Il lui sera donc alloué la somme de 150 € au titre de l’article 700 du code de procédure civile.\n  \nPAR CES MOTIFS\n\nLe tribunal statuant publiquement par mise à disposition aux greffes par jugement réputé contradictoire et en premier ressort,\n\nPrononce la résolution du contrat signé entre la SCI HERFLO et l’ETABLISSEMENT [F] en date 25 mai 2023 (facture N°14 et devis N°47), à compter de la présente décision.\n\nEn conséquence, \n\nCondamne l’ETABLISSEMENT [F] à rembourser à la SCI HERFLO la somme de 866.50 €.\n\nCondamne l’ETABLISSEMENT [F] à verser à la SCI HERFLO la somme de 150 € au titre de l’article 700 du code de procédure civile.\n\n\nLe Greffier, La Présidente,", "jurisdiction": "tj", "chamber": "DROIT COMMUN", "number": "24/00878", "numbers": ["24/00878"], "location": "tj86194", "decision_date": "2025-03-14", "decision_datetime": "2025-03-14T00:00:00.000Z", "update_date": "2025-03-15", "update_datetime": "2025-03-14T22:25:00.254Z", "solution": "Fait droit à une partie des demandes du ou des demandeurs sans accorder de délais d'exécution au défendeur", "type": "other", "nac": "50B", "portalis": null, "files": [], "zones": {"introduction": [{"start": 0, "end": 874}], "expose": [{"start": 874, "end": 2031}], "motivations": [{"start": 2031, "end": 4718}], "dispositif": [{"start": 4718, "end": 5287}]}, "contested": null, "forward": null, "timeline": null, "partial": false, "visa": [], "rapprochements": [], "legacy": {}, "titlesAndSummaries": [], "particularInterest": false}