{"id": "67d9c65183aab7e661bcb875", "source": "juritj", "text": "COUR D’APPEL DE [Localité 5]\nTRIBUNAL JUDICIAIRE DE LYON\n[Adresse 3]\n[Localité 4]\n\nN RG 25/00993 - N Portalis DB2H-W-B7J-2QFS\nOrdonnance du : 18 Mars 2025\n\nORDONNANCE DE MAINTIEN EN HOSPITALISATION COMPLÈTE\n SANS CONSENTEMENT\n\nNous, Sandrine CLOCHER-DOBREMETZ, juge au Tribunal judiciaire de Lyon, assistée de Anne-Bérangère RUBAT, greffier,\n\nVu la décision du directeur du CENTRE HOSPITALIER DU VINATIER en date du 28.02.2025, prononçant la transformation d’une mesure de soins à la demande d’un tiers en hospitalisation complète sous forme de programme de soins conformément aux articles L.3211-11-1, L.3212-1et suivants du Code de la Santé Publique,\n\nVu la décision du directeur du CENTRE HOSPITALIER DU VINATIER en date du 07.03.2025, prononçant la transformation d’une mesure de soins à la demande d’un tiers sous forme de programme de soins en hospitalisation complète conformément aux articles L.3211-11-1, L.3212-1et suivants du Code de la Santé Publique,\n\nConcernant :\nMonsieur [X] [C]\nné le 14 Mai 1986 au MAROC\n\nVu la requête en date du 14 Mars 2025 du CENTRE HOSPITALIER LE VINATIER reçue au greffe le 14 Mars 2025 et les pièces jointes à la saisine,\n\nVu les avis d’audience adressés avec la requête le 17.03.2025 au patient, au tiers ayant demandé l’admission, au directeur de l’hôpital, à l’avocat de permanence et au procureur de la République,\n\nVu l’avis du Ministère Public tendant au maintien de la mesure,\n\nAprès avoir entendu, dans les locaux spécialement aménagés de l’hôpital, en audience publique : Monsieur [X] [C] assisté de Maître FREYCHET Sophie, avocat de permanence, \n\nAttendu qu’il est attesté par l’avis motivé en vue de l’audience du Docteur [P] [T] [D], médecin de l’établissement, en date du 14.03.2025 que l’hospitalisation sous contrainte de Monsieur [X] [C] doit se poursuivre nécessairement ;\n\nQu’il résulte de cet avis que l’état mental du patient impose des soins immédiats et actuels assortis d’une surveillance médicale constante justifiant le maintien en hospitalisation complète ; \n\nAttendu que les conditions prévues par l’article L. 3212-1 du Code de la Santé Publique sont toujours remplies ;\n\nPAR CES MOTIFS\n\nStatuant publiquement et en 1er ressort,\n\nAutorisons le maintien en hospitalisation complète de Monsieur [X] [C] sans son consentement pour lui prodiguer des soins psychiatriques au-delà d’une durée de douze jours ;\n\nLaissons les dépens à la charge du Trésor ;\n\nRappelons qu’appel peut être interjeté de cette décision dans un délai de 10 jours à compter de sa notification, par déclaration écrite motivée transmise par tout moyen au greffe de la Cour d’appel \n([Adresse 2] - Tél : [XXXXXXXX01]).\n\nLe 18 Mars 2025\nLe Juge\nSandrine CLOCHER-DOBREMETZ\n\n\n\n\n\nN RG 25/00993 - N Portalis DB2H-W-B7J-2QFS\n\n- Copie de l’ordonnance a été remise en main propre à Monsieur [X] [C] le 18 Mars 2025,\nL’intéressé, \n\n\n\n\n- Copie de l’ordonnance a été remise en main propre à l’avocat de permanence le 18 Mars 2025\nL’avocat, \n\n\n\n\n\n- Copie de l’ordonnance a été remise en main propre au directeur du CENTRE HOSPITALIER LE VINATIER le 18 Mars 2025\n\n- Copie de l’ordonnance a été notifiée par lettre simple au tiers ayant demandé l’admission le 18 Mars 2025 \n\n- Avis de la présente ordonnance a été donné au procureur de la République le 18 Mars 2025.\n\nLe Greffier,", "jurisdiction": "tj", "chamber": "J.L.D.", "number": "25/00993", "numbers": ["25/00993"], "location": "tj69123", "decision_date": "2025-03-18", "decision_datetime": "2025-03-18T00:00:00.000Z", "update_date": "2025-03-18", "update_datetime": "2025-03-18T19:15:02.985Z", "solution": "Maintien de la mesure de soins psychiatriques", "type": "other", "nac": "14K", "portalis": null, "files": [], "zones": {"introduction": [{"start": 0, "end": 342}], "expose": [{"start": 342, "end": 1597}], "motivations": [{"start": 1597, "end": 2141}], "dispositif": [{"start": 2141, "end": 3302}]}, "contested": null, "forward": null, "timeline": null, "partial": false, "visa": [], "rapprochements": [], "legacy": {}, "titlesAndSummaries": [], "particularInterest": false}