{"id": "682631d01bda0e3a8e190efe", "source": "juritj", "text": "TRIBUNAL\n JUDICIAIRE\n DE [Localité 2]\n\n ■\n\n\n\n6ème chambre 2ème section\n\n N° RG 22/15115 - N° Portalis 352J-W-B7G-CYOBF\n\n\n\nDEMANDEURS\nMme [L] [V]\nM. [J] [V]\nS.A.R.L. [Adresse 1]\nAVOCATs DEMANDEURS\nreprésentée par Maître [S] [M] de la SELARL LEGABAT - #P0548\nreprésenté par Maître [S] [M] de la SELARL LEGABAT - #P0548\nreprésentée par Maître [S] [M] de la SELARL LEGABAT - #P0548\nDEFENDEURS\nCompagnie d’assurance CASUALTY & GENERAL INSURANCE COMPANY EUROPE LIMITE\nM. [G] [I]\nS.A.R.L. ECOTRA\nS.C.P. BR ASSOCIES\nS.E.L.A.R.L. [Y] [O] & ASSOCIES\nM. [A] [D]\nCompagnie d’assurance MAF\nS.A.R.L. MPCAC\nCompagnie d’assurance CASUALTY & GENERAL INSURANCE COMPANY EUROPE LIMITED assureur de la société MPCAC\nCompagnie d’assurance DIRECT ASSURANCES\nCompagnie d’assurance MAAF ASSURANCES SA\nAVOCATs DEFENDEURS\ndéfaillant\ndéfaillant\ndéfaillant\ndéfaillant\ndéfaillant\ndéfaillant\nreprésenté par Maître [C] [P] de la SELAS LARRIEU ET ASSOCIES - #J0073\ndéfaillant\nreprésenté par Maître [X] [F] de la SELAS LHUMEAU [R] HENNEQUIN & ASSOCIES - #P0483\ndéfaillant\nreprésenté par Me Juliette MEL - #E2254\n\nORDONNANCE DE CLÔTURE\n\nNous, Stéphanie VIAUD, Juge\nAssisté de Audrey BABA, Greffier,\n\nVu les articles 799 et suivants du code de procédure civile,\n\nAttendu que la procédure est en état et l’affaire susceptible d’être jugée au fond ;\n\nAttendu que les délais impartis pour communiquer les pièces et pour conclure sont expirés ; que la clôture de l’instruction est requise.\n\nDéclarons l’instruction close.\n\nLe 02 mai 2025\nLe Greffier Le Juge de la mise en état\n\n\n\n\n\nAVIS\nMaître,\n\nJe vous informe que cette affaire est définitivement fixée pour être plaidée ou radiée par jugement à l’audience juge rapporteur\n\nen date du vendredi 13 mars 2026 à 9h35\n\n\nIl est rappelé que les parties peuvent saisir le juge de la mise en état, à tout moment, pour solliciter la désignation d'un médiateur judiciaire (laquelle serait alors immédiatement ordonnée) ou l'homologation d'un protocole d'accord.\n\nLes parties sont invitées, sous réserve de leur acceptation et des possibilités matérielles, à produire au tribunal une version numérique (USB) de leur dossier de plaidoirie. Les pièces seront numérotées et nommées selon l’ordre du bordereau.\n\nLe 02/05/2025 Le Juge de la mise en état\n\nATTENTION\npièces classées suivant bordereau et un exemplaire papier des dernières conclusions à adresser \n15 jours avant l’audience", "jurisdiction": "tj", "chamber": "6ème chambre 2ème section", "number": "22/15115", "numbers": ["22/15115"], "location": "tj75056", "decision_date": "2025-05-02", "decision_datetime": "2025-05-02T00:00:00.000Z", "update_date": "2025-05-15", "update_datetime": "2025-05-15T18:26:24.967Z", "solution": "MEE : Renvoi avec ordonnance de clôture et renvoi en plaidoirie", "type": "other", "nac": "54G", "portalis": null, "files": [], "zones": {"introduction": [{"start": 0, "end": 1164}], "expose": [{"start": 1164, "end": 1226}], "motivations": [{"start": 1226, "end": 1451}], "dispositif": [{"start": 1451, "end": 2383}]}, "contested": null, "forward": null, "timeline": null, "partial": false, "visa": [], "rapprochements": [], "legacy": {}, "titlesAndSummaries": [], "particularInterest": false}